Metadata-Version: 2.1
Name: current-time
Version: 0.0.1
Summary: Time Display
Home-page: 
Author: Stephen Angelo
Author-email: stephenangeloirl@gmail.com
License: MIT
Keywords: timedisplay
Classifier: Development Status :: 5 - Production/Stable
Classifier: Intended Audience :: Education
Classifier: Operating System :: Microsoft :: Windows :: Windows 10
Classifier: License :: OSI Approved :: MIT License
Classifier: Programming Language :: Python :: 3
License-File: LICENCE.txt
